LICENSE
MANIFEST.in
README.md
setup.py
ab_test_platform/__init__.py
ab_test_platform/ab_test.py
ab_test_platform/configs.py
ab_test_platform/data_access.py
ab_test_platform/executor.py
ab_test_platform/functions.py
ab_test_platform/main.py
ab_test_platform/scheduler_service.py
ab_test_platform/utils.py
ab_test_platform/docs/ab_test_execute.yaml
ab_test_platform/docs/apis.yaml
ab_test_platform/docs/configs.yaml
ab_test_platform/docs/test_parameters.yaml
abtest.egg-info/PKG-INFO
abtest.egg-info/SOURCES.txt
abtest.egg-info/dependency_links.txt
abtest.egg-info/requires.txt
abtest.egg-info/top_level.txt