Metadata-Version: 2.1
Name: abtest
Version: 0.0.7
Summary: allows to run AB Test for any problem, automatically decides which test must be applied and represents the results
Home-page: https://github.com/caglanakpinar/abtp
Author: Caglan Akpinar
Author-email: cakpinar23@gmail.com
License: UNKNOWN
Keywords: A-B Test Control - Active Group Test AB Test via Bayesian Approach
Platform: UNKNOWN
Classifier: Programming Language :: Python :: 3
Classifier: License :: OSI Approved :: MIT License
Classifier: Operating System :: OS Independent
Requires-Python: >=3
